LICENSE
MANIFEST.in
README.rst
setup.py
RedCache.egg-info/PKG-INFO
RedCache.egg-info/SOURCES.txt
RedCache.egg-info/dependency_links.txt
RedCache.egg-info/not-zip-safe
RedCache.egg-info/requires.txt
RedCache.egg-info/top_level.txt
docs/.gitignore
docs/Makefile
docs/source/conf.py
docs/source/index.rst
docs/source/api/cache_manager.rst
docs/source/api/connection.rst
redcache/__init__.py
redcache/cache_manager.py
redcache/connection.py
redcache/local.py
tests/test_cache_mananger.py
tests/test_cache_mananger.pyc
tests/test_connection.py
tests/test_connection.pyc
tests/test_default_cache.py
tests/test_default_cache.pyc
tests/test_keygen.py
tests/test_keygen.pyc