Metadata-Version: 1.1
Name: RedCache
Version: 0.3
Summary: Lightweight and extensible caching framework for Python applications. It uses Redis as its storage backend.
Home-page: http://tomekwojcik.github.io/redcache/
Author: Tomasz Wójcik
Author-email: tomek@bthlabs.pl
License: https://github.com/tomekwojcik/redcache/blob/master/LICENSE
Download-URL: https://github.com/tomekwojcik/redcache/tarball/v0.3
Platform: any
Classifier: Development Status :: 4 - Beta
Classifier: Intended Audience :: Developers
Classifier: License :: OSI Approved :: BSD License
Classifier: Operating System :: OS Independent
Classifier: Programming Language :: Python
Classifier: Topic :: Software Development :: Libraries :: Python Modules
